[
  {
    "title": "Navyblue Kol Nakışlı Takım",
    "img": [
      "https://maxtaylor.com.tr/koleksiyon/canta/images/urun/7/2594-99-1.jpg?3",
      "https://maxtaylor.com.tr/koleksiyon/canta/images/urun/7/2594-99-2.jpg?3"
    ],
    "primaryImg": "/images/urun/3/2594-99-1.jpg?3 180w 230h,/images/urun/4/2594-99-1.jpg?3 360w 460h,/images/urun/5/2594-99-1.jpg?3 540w 690h,/images/urun/6/2594-99-1.jpg?3 720w 920h,/images/urun/7/2594-99-1.jpg?3 900w 1150h,/images/urun/8/2594-99-1.jpg?3 1080w 1380h,/images/urun/9/2594-99-1.jpg?3 1296w 1656h,/images/urun/10/2594-99-1.jpg?3 1512w 1932h,/images/urun/11/2594-99-1.jpg?3 1728w 2208h,/images/urun/12/2594-99-1.jpg?3 1800w 2300h",
    "link": "https://maxtaylor.com.tr/en/product/bayan-navyblue-kol-nak%C4%B1%C5%9Fl%C4%B1-tak%C4%B1m-2594-99",
    "price": [
      {
        "value": "$ 64.1,00",
        "selector": ".money.tutar",
        "attribute": "textContent",
        "isJavaScript": false,
        "isShadowDOM": false,
        "numericValue": 0,
        "unsetPrice": true
      }
    ],
    "videos": [],
    "productNotInStock": false,
    "matchedInfo": {
      "linkSource": "titleElement (matched: .name a)",
      "matchedSelector": ".yit-wcan-container .product.product-item.grid",
      "titleSelectorMatched": ".name a",
      "imgSelectorMatched": "[data-bgset]",
      "videoSelectorMatched": null,
      "bestPriceSelector": ".money.tutar",
      "priceExtractedFromShadowDOM": false
    },
    "pageTitle": "Maxtaylor",
    "pageURL": "https://maxtaylor.com.tr/en/collection",
    "timestamp": "2025-09-10T05:15:18.351Z",
    "imgValid": true,
    "linkValid": true,
    "titleValid": true,
    "pageTitleValid": true,
    "priceValid": false,
    "videoValid": false,
    "mediaType": "image",
    "processId": "mfdj008b1o9fu",
    "index": 14
  },
  {
    "title": "Pink Şal Yaka Etekli Takım",
    "img": [
      "https://maxtaylor.com.tr/koleksiyon/canta/images/urun/7/2550-129-1.jpg?4"
    ],
    "primaryImg": "/images/urun/3/2550-129-1.jpg?4 180w 230h,/images/urun/4/2550-129-1.jpg?4 360w 460h,/images/urun/5/2550-129-1.jpg?4 540w 690h,/images/urun/6/2550-129-1.jpg?4 720w 920h,/images/urun/7/2550-129-1.jpg?4 900w 1150h,/images/urun/8/2550-129-1.jpg?4 1080w 1380h,/images/urun/9/2550-129-1.jpg?4 1296w 1656h,/images/urun/10/2550-129-1.jpg?4 1512w 1932h,/images/urun/11/2550-129-1.jpg?4 1728w 2208h,/images/urun/12/2550-129-1.jpg?4 1800w 2300h",
    "link": "https://maxtaylor.com.tr/en/product/bayan-pink-%C5%9Fal-yaka-etekli-tak%C4%B1m-2550-129",
    "price": [
      {
        "value": "$ 64.1,00",
        "selector": ".money.tutar",
        "attribute": "textContent",
        "isJavaScript": false,
        "isShadowDOM": false,
        "numericValue": 0,
        "unsetPrice": true
      }
    ],
    "videos": [],
    "productNotInStock": false,
    "matchedInfo": {
      "linkSource": "titleElement (matched: .name a)",
      "matchedSelector": ".yit-wcan-container .product.product-item.grid",
      "titleSelectorMatched": ".name a",
      "imgSelectorMatched": "[data-bgset]",
      "videoSelectorMatched": null,
      "bestPriceSelector": ".money.tutar",
      "priceExtractedFromShadowDOM": false
    },
    "pageTitle": "Maxtaylor",
    "pageURL": "https://maxtaylor.com.tr/en/collection",
    "timestamp": "2025-09-10T05:15:18.379Z",
    "imgValid": true,
    "linkValid": true,
    "titleValid": true,
    "pageTitleValid": true,
    "priceValid": false,
    "videoValid": false,
    "mediaType": "image",
    "processId": "mfdj008b1o9fu",
    "index": 24
  },
  {
    "title": "Baby Blue Şal Yaka Etekli Takım",
    "img": [
      "https://maxtaylor.com.tr/koleksiyon/canta/images/urun/7/2550-22-1.jpg?4"
    ],
    "primaryImg": "/images/urun/3/2550-22-1.jpg?4 180w 230h,/images/urun/4/2550-22-1.jpg?4 360w 460h,/images/urun/5/2550-22-1.jpg?4 540w 690h,/images/urun/6/2550-22-1.jpg?4 720w 920h,/images/urun/7/2550-22-1.jpg?4 900w 1150h,/images/urun/8/2550-22-1.jpg?4 1080w 1380h,/images/urun/9/2550-22-1.jpg?4 1296w 1656h,/images/urun/10/2550-22-1.jpg?4 1512w 1932h,/images/urun/11/2550-22-1.jpg?4 1728w 2208h,/images/urun/12/2550-22-1.jpg?4 1800w 2300h",
    "link": "https://maxtaylor.com.tr/en/product/bayan-baby-blue-%C5%9Fal-yaka-etekli-tak%C4%B1m-2550-22",
    "price": [
      {
        "value": "$ 64.1,00",
        "selector": ".money.tutar",
        "attribute": "textContent",
        "isJavaScript": false,
        "isShadowDOM": false,
        "numericValue": 0,
        "unsetPrice": true
      }
    ],
    "videos": [],
    "productNotInStock": false,
    "matchedInfo": {
      "linkSource": "titleElement (matched: .name a)",
      "matchedSelector": ".yit-wcan-container .product.product-item.grid",
      "titleSelectorMatched": ".name a",
      "imgSelectorMatched": "[data-bgset]",
      "videoSelectorMatched": null,
      "bestPriceSelector": ".money.tutar",
      "priceExtractedFromShadowDOM": false
    },
    "pageTitle": "Maxtaylor",
    "pageURL": "https://maxtaylor.com.tr/en/collection",
    "timestamp": "2025-09-10T05:15:18.381Z",
    "imgValid": true,
    "linkValid": true,
    "titleValid": true,
    "pageTitleValid": true,
    "priceValid": false,
    "videoValid": false,
    "mediaType": "image",
    "processId": "mfdj008b1o9fu",
    "index": 25
  },
  {
    "title": "Navyblue Şalvar Takım",
    "img": [
      "https://maxtaylor.com.tr/koleksiyon/canta/images/urun/7/2571-99-1.jpg?16",
      "https://maxtaylor.com.tr/koleksiyon/canta/images/urun/7/2571-99-2.jpg?16"
    ],
    "primaryImg": "/images/urun/3/2571-99-1.jpg?16 180w 230h,/images/urun/4/2571-99-1.jpg?16 360w 460h,/images/urun/5/2571-99-1.jpg?16 540w 690h,/images/urun/6/2571-99-1.jpg?16 720w 920h,/images/urun/7/2571-99-1.jpg?16 900w 1150h,/images/urun/8/2571-99-1.jpg?16 1080w 1380h,/images/urun/9/2571-99-1.jpg?16 1296w 1656h,/images/urun/10/2571-99-1.jpg?16 1512w 1932h,/images/urun/11/2571-99-1.jpg?16 1728w 2208h,/images/urun/12/2571-99-1.jpg?16 1800w 2300h",
    "link": "https://maxtaylor.com.tr/en/product/bayan-navyblue-%C5%9Falvar-tak%C4%B1m-2571-99",
    "price": [
      {
        "value": "$ 64.1,00",
        "selector": ".money.tutar",
        "attribute": "textContent",
        "isJavaScript": false,
        "isShadowDOM": false,
        "numericValue": 0,
        "unsetPrice": true
      }
    ],
    "videos": [],
    "productNotInStock": false,
    "matchedInfo": {
      "linkSource": "titleElement (matched: .name a)",
      "matchedSelector": ".yit-wcan-container .product.product-item.grid",
      "titleSelectorMatched": ".name a",
      "imgSelectorMatched": "[data-bgset]",
      "videoSelectorMatched": null,
      "bestPriceSelector": ".money.tutar",
      "priceExtractedFromShadowDOM": false
    },
    "pageTitle": "Maxtaylor",
    "pageURL": "https://maxtaylor.com.tr/en/collection",
    "timestamp": "2025-09-10T05:15:18.408Z",
    "imgValid": true,
    "linkValid": true,
    "titleValid": true,
    "pageTitleValid": true,
    "priceValid": false,
    "videoValid": false,
    "mediaType": "image",
    "processId": "mfdj008b1o9fu",
    "index": 37
  }
]