{
  "uniqueSelectors": {},
  "selectorUsage": {
    ".o-productList__itemWrapper": {
      "count": 48,
      "usedFor": {},
      "objectIndices": [
        0,
        1,
        2,
        3,
        4,
        5,
        6,
        7,
        8,
        9,
        10,
        11,
        12,
        13,
        14,
        15,
        16,
        17,
        18,
        19,
        20,
        21,
        22,
        23,
        24,
        25,
        26,
        27,
        28,
        29,
        30,
        31,
        32,
        33,
        34,
        35,
        36,
        37,
        38,
        39,
        40,
        41,
        42,
        43,
        44,
        45,
        46,
        47
      ]
    },
    ".m-productCard__desc": {
      "count": 48,
      "usedFor": {},
      "objectIndices": [
        0,
        1,
        2,
        3,
        4,
        5,
        6,
        7,
        8,
        9,
        10,
        11,
        12,
        13,
        14,
        15,
        16,
        17,
        18,
        19,
        20,
        21,
        22,
        23,
        24,
        25,
        26,
        27,
        28,
        29,
        30,
        31,
        32,
        33,
        34,
        35,
        36,
        37,
        38,
        39,
        40,
        41,
        42,
        43,
        44,
        45,
        46,
        47
      ]
    },
    "[data-srcset]": {
      "count": 48,
      "usedFor": {},
      "objectIndices": [
        0,
        1,
        2,
        3,
        4,
        5,
        6,
        7,
        8,
        9,
        10,
        11,
        12,
        13,
        14,
        15,
        16,
        17,
        18,
        19,
        20,
        21,
        22,
        23,
        24,
        25,
        26,
        27,
        28,
        29,
        30,
        31,
        32,
        33,
        34,
        35,
        36,
        37,
        38,
        39,
        40,
        41,
        42,
        43,
        44,
        45,
        46,
        47
      ]
    },
    ".m-productCard__newPrice": {
      "count": 48,
      "usedFor": {},
      "objectIndices": [
        0,
        1,
        2,
        3,
        4,
        5,
        6,
        7,
        8,
        9,
        10,
        11,
        12,
        13,
        14,
        15,
        16,
        17,
        18,
        19,
        20,
        21,
        22,
        23,
        24,
        25,
        26,
        27,
        28,
        29,
        30,
        31,
        32,
        33,
        34,
        35,
        36,
        37,
        38,
        39,
        40,
        41,
        42,
        43,
        44,
        45,
        46,
        47
      ]
    }
  },
  "summary": {
    "totalObjects": 48,
    "selectorsFound": 4,
    "mostCommonSelectors": [
      {
        "selector": ".o-productList__itemWrapper",
        "count": 48,
        "usedFor": [
          "main element"
        ]
      },
      {
        "selector": ".m-productCard__desc",
        "count": 48,
        "usedFor": [
          "title"
        ]
      },
      {
        "selector": "[data-srcset]",
        "count": 48,
        "usedFor": [
          "image"
        ]
      },
      {
        "selector": ".m-productCard__newPrice",
        "count": 48,
        "usedFor": [
          "price"
        ]
      }
    ]
  }
}