{
  "uniqueSelectors": {},
  "selectorUsage": {
    "#ProductPageProductList .ItemOrj .productItem": {
      "count": 101,
      "usedFor": {}
    },
    ".productName a": {
      "count": 101,
      "usedFor": {}
    },
    "img.productSliderImage": {
      "count": 101,
      "usedFor": {}
    },
    ".discountPrice .discountPriceSpan": {
      "count": 101,
      "usedFor": {}
    }
  },
  "summary": {
    "totalObjects": 101,
    "selectorsFound": 4,
    "mostCommonSelectors": [
      {
        "selector": "#ProductPageProductList .ItemOrj .productItem",
        "count": 101,
        "usedFor": [
          "main element"
        ]
      },
      {
        "selector": ".productName a",
        "count": 101,
        "usedFor": [
          "title"
        ]
      },
      {
        "selector": "img.productSliderImage",
        "count": 101,
        "usedFor": [
          "image"
        ]
      },
      {
        "selector": ".discountPrice .discountPriceSpan",
        "count": 101,
        "usedFor": [
          "price"
        ]
      }
    ]
  }
}