[
  {
    "title": "Kadın",
    "img": [],
    "primaryImg": null,
    "link": "https://tr.benetton.com/kadin",
    "price": [],
    "videos": [],
    "productNotInStock": false,
    "matchedInfo": {
      "linkSource": "titleElement (matched: a[title]:not([href='javascript:void(0);']):not([href='#']):not([href='']))",
      "matchedSelector": "div[data-id]",
      "titleSelectorMatched": "a[title]:not([href='javascript:void(0);']):not([href='#']):not([href=''])",
      "imgSelectorMatched": null,
      "videoSelectorMatched": null,
      "bestPriceSelector": null,
      "priceExtractedFromShadowDOM": false
    },
    "pageTitle": "Çanta, Kadın Çanta Modelleri | Benetton",
    "pageURL": "https://tr.benetton.com/kadin-canta",
    "timestamp": "2025-09-09T12:20:30.904Z",
    "imgValid": false,
    "linkValid": true,
    "titleValid": true,
    "pageTitleValid": true,
    "priceValid": false,
    "videoValid": false,
    "mediaType": "image",
    "processId": "mfciqzkqyk9z1",
    "index": 0
  },
  {
    "title": "Erkek",
    "img": [],
    "primaryImg": null,
    "link": "https://tr.benetton.com/erkek",
    "price": [],
    "videos": [],
    "productNotInStock": false,
    "matchedInfo": {
      "linkSource": "titleElement (matched: a[title]:not([href='javascript:void(0);']):not([href='#']):not([href='']))",
      "matchedSelector": "div[data-id]",
      "titleSelectorMatched": "a[title]:not([href='javascript:void(0);']):not([href='#']):not([href=''])",
      "imgSelectorMatched": null,
      "videoSelectorMatched": null,
      "bestPriceSelector": null,
      "priceExtractedFromShadowDOM": false
    },
    "pageTitle": "Çanta, Kadın Çanta Modelleri | Benetton",
    "pageURL": "https://tr.benetton.com/kadin-canta",
    "timestamp": "2025-09-09T12:20:30.907Z",
    "imgValid": false,
    "linkValid": true,
    "titleValid": true,
    "pageTitleValid": true,
    "priceValid": false,
    "videoValid": false,
    "mediaType": "image",
    "processId": "mfciqzkqyk9z1",
    "index": 1
  },
  {
    "title": "Çocuk",
    "img": [],
    "primaryImg": null,
    "link": "https://tr.benetton.com/cocuk",
    "price": [],
    "videos": [],
    "productNotInStock": false,
    "matchedInfo": {
      "linkSource": "titleElement (matched: a[title]:not([href='javascript:void(0);']):not([href='#']):not([href='']))",
      "matchedSelector": "div[data-id]",
      "titleSelectorMatched": "a[title]:not([href='javascript:void(0);']):not([href='#']):not([href=''])",
      "imgSelectorMatched": null,
      "videoSelectorMatched": null,
      "bestPriceSelector": null,
      "priceExtractedFromShadowDOM": false
    },
    "pageTitle": "Çanta, Kadın Çanta Modelleri | Benetton",
    "pageURL": "https://tr.benetton.com/kadin-canta",
    "timestamp": "2025-09-09T12:20:30.910Z",
    "imgValid": false,
    "linkValid": true,
    "titleValid": true,
    "pageTitleValid": true,
    "priceValid": false,
    "videoValid": false,
    "mediaType": "image",
    "processId": "mfciqzkqyk9z1",
    "index": 2
  },
  {
    "title": "UNDERCOLORS",
    "img": [],
    "primaryImg": null,
    "link": "https://tr.benetton.com/undercolors",
    "price": [],
    "videos": [],
    "productNotInStock": false,
    "matchedInfo": {
      "linkSource": "titleElement (matched: a[title]:not([href='javascript:void(0);']):not([href='#']):not([href='']))",
      "matchedSelector": "div[data-id]",
      "titleSelectorMatched": "a[title]:not([href='javascript:void(0);']):not([href='#']):not([href=''])",
      "imgSelectorMatched": null,
      "videoSelectorMatched": null,
      "bestPriceSelector": null,
      "priceExtractedFromShadowDOM": false
    },
    "pageTitle": "Çanta, Kadın Çanta Modelleri | Benetton",
    "pageURL": "https://tr.benetton.com/kadin-canta",
    "timestamp": "2025-09-09T12:20:30.913Z",
    "imgValid": false,
    "linkValid": true,
    "titleValid": true,
    "pageTitleValid": true,
    "priceValid": false,
    "videoValid": false,
    "mediaType": "image",
    "processId": "mfciqzkqyk9z1",
    "index": 3
  },
  {
    "title": "Sürdürülebilirlik",
    "img": [],
    "primaryImg": null,
    "link": "https://tr.benetton.com/I/surdurulebilirlik",
    "price": [],
    "videos": [],
    "productNotInStock": false,
    "matchedInfo": {
      "linkSource": "titleElement (matched: a[title]:not([href='javascript:void(0);']):not([href='#']):not([href='']))",
      "matchedSelector": "div[data-id]",
      "titleSelectorMatched": "a[title]:not([href='javascript:void(0);']):not([href='#']):not([href=''])",
      "imgSelectorMatched": null,
      "videoSelectorMatched": null,
      "bestPriceSelector": null,
      "priceExtractedFromShadowDOM": false
    },
    "pageTitle": "Çanta, Kadın Çanta Modelleri | Benetton",
    "pageURL": "https://tr.benetton.com/kadin-canta",
    "timestamp": "2025-09-09T12:20:30.915Z",
    "imgValid": false,
    "linkValid": true,
    "titleValid": true,
    "pageTitleValid": true,
    "priceValid": false,
    "videoValid": false,
    "mediaType": "image",
    "processId": "mfciqzkqyk9z1",
    "index": 4
  }
]