[
  {
    "title": "Geronimo Krem Alışveriş Çantası",
    "img": [
      "https://cdn.beymen.com/mnresize/850/-/productimages/bbtr4x1a.omy_IMG_01_2110094847615.jpg",
      "https://cdn.beymen.com/mnresize/425/-/productimages/bbtr4x1a.omy_IMG_01_2110094847615.jpg",
      "https://cdn.beymen.com/mnresize/{width}/{height}/productimages/bbtr4x1a.omy_IMG_01_2110094847615.jpg",
      "https://cdn.beymen.com/mnresize/{width}/{height}/productimages/zt5brvog.jga_IMG_02_2110094847615.jpg",
      "https://cdn.beymen.com/mnresize/{width}/{height}/productimages/atkxarzr.hnb_IMG_03_2110094847615.jpg",
      "https://cdn.beymen.com/mnresize/{width}/{height}/productimages/we1hbhul.emu_IMG_04_2110094847615.jpg"
    ],
    "primaryImg": "https://cdn.beymen.com/mnresize/425/-/productimages/bbtr4x1a.omy_IMG_01_2110094847615.jpg, https://cdn.beymen.com/mnresize/850/-/productimages/bbtr4x1a.omy_IMG_01_2110094847615.jpg 2x",
    "link": "https://www.beymen.com/tr/p_beymen-geronimo-krem-alisveris-cantasi_1402193",
    "price": [
      {
        "value": "3.999 TL",
        "selector": ".m-productCard__newPrice",
        "attribute": "textContent",
        "isJavaScript": false,
        "isShadowDOM": false,
        "numericValue": 3999,
        "unsetPrice": false
      }
    ],
    "videos": [],
    "productNotInStock": false,
    "matchedInfo": {
      "linkSource": "linkElement (matched: .m-productCard__detail h3 > :nth-child(2))",
      "matchedSelector": ".o-productList__itemWrapper",
      "titleSelectorMatched": ".m-productCard__desc",
      "imgSelectorMatched": "[data-srcset]",
      "videoSelectorMatched": null,
      "bestPriceSelector": ".m-productCard__newPrice",
      "priceExtractedFromShadowDOM": false
    },
    "pageTitle": "2025 Kadın Çanta Marka & Modelleri | Beymen",
    "pageURL": "https://www.beymen.com/tr/kadin-canta-10019",
    "timestamp": "2025-08-29T10:18:54.889Z",
    "imgValid": true,
    "linkValid": true,
    "titleValid": true,
    "pageTitleValid": true,
    "priceValid": true,
    "videoValid": false,
    "mediaType": "image"
  },
  {
    "title": "Bonnie Krem Kadın Omuz Çantası",
    "img": [
      "https://cdn.beymen.com/mnresize/850/-/productimages/yprhiitd.cea_IMG_01_2110094847646.jpg",
      "https://cdn.beymen.com/mnresize/425/-/productimages/yprhiitd.cea_IMG_01_2110094847646.jpg",
      "https://cdn.beymen.com/mnresize/{width}/{height}/productimages/yprhiitd.cea_IMG_01_2110094847646.jpg",
      "https://cdn.beymen.com/mnresize/{width}/{height}/productimages/qmwtijhh.yen_IMG_02_2110094847646.jpg",
      "https://cdn.beymen.com/mnresize/{width}/{height}/productimages/tqfhj4ko.rpi_IMG_03_2110094847646.jpg",
      "https://cdn.beymen.com/mnresize/{width}/{height}/productimages/13frr3x4.qg2_IMG_04_2110094847646.jpg"
    ],
    "primaryImg": "https://cdn.beymen.com/mnresize/425/-/productimages/yprhiitd.cea_IMG_01_2110094847646.jpg, https://cdn.beymen.com/mnresize/850/-/productimages/yprhiitd.cea_IMG_01_2110094847646.jpg 2x",
    "link": "https://www.beymen.com/tr/p_beymen-bonnie-krem-kadin-omuz-cantasi_1402134",
    "price": [
      {
        "value": "2.749 TL",
        "selector": ".m-productCard__newPrice",
        "attribute": "textContent",
        "isJavaScript": false,
        "isShadowDOM": false,
        "numericValue": 2749,
        "unsetPrice": false
      }
    ],
    "videos": [],
    "productNotInStock": false,
    "matchedInfo": {
      "linkSource": "linkElement (matched: .m-productCard__detail h3 > :nth-child(2))",
      "matchedSelector": ".o-productList__itemWrapper",
      "titleSelectorMatched": ".m-productCard__desc",
      "imgSelectorMatched": "[data-srcset]",
      "videoSelectorMatched": null,
      "bestPriceSelector": ".m-productCard__newPrice",
      "priceExtractedFromShadowDOM": false
    },
    "pageTitle": "2025 Kadın Çanta Marka & Modelleri | Beymen",
    "pageURL": "https://www.beymen.com/tr/kadin-canta-10019",
    "timestamp": "2025-08-29T10:18:54.893Z",
    "imgValid": true,
    "linkValid": true,
    "titleValid": true,
    "pageTitleValid": true,
    "priceValid": true,
    "videoValid": false,
    "mediaType": "image"
  },
  {
    "title": "Nyluxe Siyah Seyahat Çantası",
    "img": [
      "https://cdn.beymen.com/mnresize/850/-/productimages/ebnxyfjk.kk0_IMG_01_2110099142579.jpg",
      "https://cdn.beymen.com/mnresize/425/-/productimages/ebnxyfjk.kk0_IMG_01_2110099142579.jpg",
      "https://cdn.beymen.com/mnresize/{width}/{height}/productimages/ebnxyfjk.kk0_IMG_01_2110099142579.jpg",
      "https://cdn.beymen.com/mnresize/{width}/{height}/productimages/julyq5k3.hgh_IMG_02_2110099142579.jpg",
      "https://cdn.beymen.com/mnresize/{width}/{height}/productimages/dt1p4ctx.ipt_IMG_03_2110099142579.jpg",
      "https://cdn.beymen.com/mnresize/{width}/{height}/productimages/vuejqiif.4wj_IMG_04_2110099142579.jpg"
    ],
    "primaryImg": "https://cdn.beymen.com/mnresize/425/-/productimages/ebnxyfjk.kk0_IMG_01_2110099142579.jpg, https://cdn.beymen.com/mnresize/850/-/productimages/ebnxyfjk.kk0_IMG_01_2110099142579.jpg 2x",
    "link": "https://www.beymen.com/tr/p_beymen-nyluxe-siyah-seyahat-cantasi_1641044",
    "price": [
      {
        "value": "4.999 TL",
        "selector": ".m-productCard__newPrice",
        "attribute": "textContent",
        "isJavaScript": false,
        "isShadowDOM": false,
        "numericValue": 4999,
        "unsetPrice": false
      }
    ],
    "videos": [],
    "productNotInStock": false,
    "matchedInfo": {
      "linkSource": "linkElement (matched: .m-productCard__detail h3 > :nth-child(2))",
      "matchedSelector": ".o-productList__itemWrapper",
      "titleSelectorMatched": ".m-productCard__desc",
      "imgSelectorMatched": "[data-srcset]",
      "videoSelectorMatched": null,
      "bestPriceSelector": ".m-productCard__newPrice",
      "priceExtractedFromShadowDOM": false
    },
    "pageTitle": "2025 Kadın Çanta Marka & Modelleri | Beymen",
    "pageURL": "https://www.beymen.com/tr/kadin-canta-10019",
    "timestamp": "2025-08-29T10:18:54.897Z",
    "imgValid": true,
    "linkValid": true,
    "titleValid": true,
    "pageTitleValid": true,
    "priceValid": true,
    "videoValid": false,
    "mediaType": "image"
  },
  {
    "title": "Kahverengi Kadın Çanta",
    "img": [
      "https://cdn.beymen.com/mnresize/850/-/productimages/ixjy43ce.p2s_IMG_01_2110100959813.jpg",
      "https://cdn.beymen.com/mnresize/425/-/productimages/ixjy43ce.p2s_IMG_01_2110100959813.jpg",
      "https://cdn.beymen.com/assets/desktop/img/beymen-placeholder-435px-606px.svg",
      "https://cdn.beymen.com/mnresize/{width}/{height}/productimages/ixjy43ce.p2s_IMG_01_2110100959813.jpg",
      "https://cdn.beymen.com/mnresize/{width}/{height}/productimages/becyahih.oqa_IMG_02_2110100959813.jpg",
      "https://cdn.beymen.com/mnresize/{width}/{height}/productimages/n2c42rdj.ung_IMG_03_2110100959813.jpg",
      "https://cdn.beymen.com/mnresize/{width}/{height}/productimages/mmilsvn2.0qk_IMG_04_2110100959813.jpg"
    ],
    "primaryImg": "https://cdn.beymen.com/mnresize/425/-/productimages/ixjy43ce.p2s_IMG_01_2110100959813.jpg, https://cdn.beymen.com/mnresize/850/-/productimages/ixjy43ce.p2s_IMG_01_2110100959813.jpg 2x",
    "link": "https://www.beymen.com/tr/p_fendi-kahverengi-kadin-canta_1676689",
    "price": [
      {
        "value": "62.950 TL",
        "selector": ".m-productCard__newPrice",
        "attribute": "textContent",
        "isJavaScript": false,
        "isShadowDOM": false,
        "numericValue": 62950,
        "unsetPrice": false
      }
    ],
    "videos": [],
    "productNotInStock": false,
    "matchedInfo": {
      "linkSource": "linkElement (matched: .m-productCard__detail h3 > :nth-child(2))",
      "matchedSelector": ".o-productList__itemWrapper",
      "titleSelectorMatched": ".m-productCard__desc",
      "imgSelectorMatched": "[data-srcset]",
      "videoSelectorMatched": null,
      "bestPriceSelector": ".m-productCard__newPrice",
      "priceExtractedFromShadowDOM": false
    },
    "pageTitle": "2025 Kadın Çanta Marka & Modelleri | Beymen",
    "pageURL": "https://www.beymen.com/tr/kadin-canta-10019",
    "timestamp": "2025-08-29T10:18:54.900Z",
    "imgValid": true,
    "linkValid": true,
    "titleValid": true,
    "pageTitleValid": true,
    "priceValid": true,
    "videoValid": false,
    "mediaType": "image"
  },
  {
    "title": "Lena Yağ Yeşili Kadın Çanta",
    "img": [
      "https://cdn.beymen.com/mnresize/850/-/productimages/42m2dq4g.owt_IMG_01_2110099142944.jpg",
      "https://cdn.beymen.com/mnresize/425/-/productimages/42m2dq4g.owt_IMG_01_2110099142944.jpg",
      "https://cdn.beymen.com/assets/desktop/img/beymen-placeholder-435px-606px.svg",
      "https://cdn.beymen.com/mnresize/{width}/{height}/productimages/42m2dq4g.owt_IMG_01_2110099142944.jpg",
      "https://cdn.beymen.com/mnresize/{width}/{height}/productimages/cs4vhymn.2zn_IMG_02_2110099142944.jpg",
      "https://cdn.beymen.com/mnresize/{width}/{height}/productimages/tz2ko5u2.lc0_IMG_03_2110099142944.jpg",
      "https://cdn.beymen.com/mnresize/{width}/{height}/productimages/5oodekwh.14u_IMG_04_2110099142944.jpg"
    ],
    "primaryImg": "https://cdn.beymen.com/mnresize/425/-/productimages/42m2dq4g.owt_IMG_01_2110099142944.jpg, https://cdn.beymen.com/mnresize/850/-/productimages/42m2dq4g.owt_IMG_01_2110099142944.jpg 2x",
    "link": "https://www.beymen.com/tr/p_beymen-lena-yag-yesili-kadin-canta_1641019",
    "price": [
      {
        "value": "3.149 TL",
        "selector": ".m-productCard__newPrice",
        "attribute": "textContent",
        "isJavaScript": false,
        "isShadowDOM": false,
        "numericValue": 3149,
        "unsetPrice": false
      }
    ],
    "videos": [],
    "productNotInStock": false,
    "matchedInfo": {
      "linkSource": "linkElement (matched: .m-productCard__detail h3 > :nth-child(2))",
      "matchedSelector": ".o-productList__itemWrapper",
      "titleSelectorMatched": ".m-productCard__desc",
      "imgSelectorMatched": "[data-srcset]",
      "videoSelectorMatched": null,
      "bestPriceSelector": ".m-productCard__newPrice",
      "priceExtractedFromShadowDOM": false
    },
    "pageTitle": "2025 Kadın Çanta Marka & Modelleri | Beymen",
    "pageURL": "https://www.beymen.com/tr/kadin-canta-10019",
    "timestamp": "2025-08-29T10:18:54.904Z",
    "imgValid": true,
    "linkValid": true,
    "titleValid": true,
    "pageTitleValid": true,
    "priceValid": true,
    "videoValid": false,
    "mediaType": "image"
  }
]