[
  {
    "title": "OTRERA\nMini Leda Blue",
    "img": [
      "https://a88cb3.cdn.akinoncloud.com/products/2023/04/18/175972/cb3671a3-a33d-445e-b0b5-64c865c4bee4_size290x376_cropCenter.jpg"
    ],
    "primaryImg": "https://a88cb3.cdn.akinoncloud.com/products/2023/04/18/175972/cb3671a3-a33d-445e-b0b5-64c865c4bee4_size290x376_cropCenter.jpg",
    "link": "https://www.edwards.com.tr/otrera-mini-leda-blue-ss22otrera079/",
    "price": [
      {
        "value": "10300 TL",
        "selector": ".product-price .product-sale-price",
        "attribute": "textContent",
        "isJavaScript": false,
        "isShadowDOM": false,
        "numericValue": 10300,
        "unsetPrice": false
      }
    ],
    "videos": [],
    "productNotInStock": false,
    "matchedInfo": {
      "linkSource": "titleElement (matched: .product-item-info  p.product-name a)",
      "matchedSelector": ".list-content-product-item:has(.product-name a)",
      "titleSelectorMatched": ".product-item-info  p.product-name a",
      "imgSelectorMatched": ".product-item-image",
      "videoSelectorMatched": null,
      "bestPriceSelector": ".product-price .product-sale-price",
      "priceExtractedFromShadowDOM": false
    },
    "pageTitle": "Sezonun trend Kadın Çanta ürünleri Edwards Online’da",
    "pageURL": "https://www.edwards.com.tr/canta/",
    "timestamp": "2025-09-20T10:35:35.159Z",
    "imgValid": true,
    "linkValid": true,
    "titleValid": true,
    "pageTitleValid": true,
    "priceValid": true,
    "videoValid": false,
    "mediaType": "image",
    "processId": "mfs4uenlckzuc",
    "index": 0,
    "categories": {
      "productType": [
        "none"
      ]
    },
    "seo": {
      "keywords": [],
      "tags": []
    }
  },
  {
    "title": "OTRERA\nTan Flotter Card Case",
    "img": [
      "https://a88cb3.cdn.akinoncloud.com/products/2022/05/31/173959/9b315633-5290-48d4-90ab-82af7d5d3d5e_size290x376_cropCenter.jpg"
    ],
    "primaryImg": "https://a88cb3.cdn.akinoncloud.com/products/2022/05/31/173959/9b315633-5290-48d4-90ab-82af7d5d3d5e_size290x376_cropCenter.jpg",
    "link": "https://www.edwards.com.tr/otrera-tan-flotter-card-case-ss22otrera036/",
    "price": [
      {
        "value": "2600 TL",
        "selector": ".product-price .product-sale-price",
        "attribute": "textContent",
        "isJavaScript": false,
        "isShadowDOM": false,
        "numericValue": 2600,
        "unsetPrice": false
      }
    ],
    "videos": [],
    "productNotInStock": false,
    "matchedInfo": {
      "linkSource": "titleElement (matched: .product-item-info  p.product-name a)",
      "matchedSelector": ".list-content-product-item:has(.product-name a)",
      "titleSelectorMatched": ".product-item-info  p.product-name a",
      "imgSelectorMatched": ".product-item-image",
      "videoSelectorMatched": null,
      "bestPriceSelector": ".product-price .product-sale-price",
      "priceExtractedFromShadowDOM": false
    },
    "pageTitle": "Sezonun trend Kadın Çanta ürünleri Edwards Online’da",
    "pageURL": "https://www.edwards.com.tr/canta/",
    "timestamp": "2025-09-20T10:35:35.162Z",
    "imgValid": true,
    "linkValid": true,
    "titleValid": true,
    "pageTitleValid": true,
    "priceValid": true,
    "videoValid": false,
    "mediaType": "image",
    "processId": "mfs4uenlckzuc",
    "index": 1,
    "categories": {
      "productType": [
        "none"
      ]
    },
    "seo": {
      "keywords": [],
      "tags": []
    }
  },
  {
    "title": "OTRERA\nBeige Flotter Card Case",
    "img": [
      "https://a88cb3.cdn.akinoncloud.com/products/2022/04/28/173281/ba2c6cef-8bbd-45bb-823c-75201fd50ab6_size290x376_cropCenter.jpg"
    ],
    "primaryImg": "https://a88cb3.cdn.akinoncloud.com/products/2022/04/28/173281/ba2c6cef-8bbd-45bb-823c-75201fd50ab6_size290x376_cropCenter.jpg",
    "link": "https://www.edwards.com.tr/otrera-beige-flotter-card-case-ss22otrera016/",
    "price": [
      {
        "value": "2600 TL",
        "selector": ".product-price .product-sale-price",
        "attribute": "textContent",
        "isJavaScript": false,
        "isShadowDOM": false,
        "numericValue": 2600,
        "unsetPrice": false
      }
    ],
    "videos": [],
    "productNotInStock": false,
    "matchedInfo": {
      "linkSource": "titleElement (matched: .product-item-info  p.product-name a)",
      "matchedSelector": ".list-content-product-item:has(.product-name a)",
      "titleSelectorMatched": ".product-item-info  p.product-name a",
      "imgSelectorMatched": ".product-item-image",
      "videoSelectorMatched": null,
      "bestPriceSelector": ".product-price .product-sale-price",
      "priceExtractedFromShadowDOM": false
    },
    "pageTitle": "Sezonun trend Kadın Çanta ürünleri Edwards Online’da",
    "pageURL": "https://www.edwards.com.tr/canta/",
    "timestamp": "2025-09-20T10:35:35.164Z",
    "imgValid": true,
    "linkValid": true,
    "titleValid": true,
    "pageTitleValid": true,
    "priceValid": true,
    "videoValid": false,
    "mediaType": "image",
    "processId": "mfs4uenlckzuc",
    "index": 2,
    "categories": {
      "productType": [
        "none"
      ]
    },
    "seo": {
      "keywords": [],
      "tags": []
    }
  },
  {
    "title": "OTRERA\nNavy Card Case",
    "img": [
      "https://a88cb3.cdn.akinoncloud.com/products/2022/04/16/173279/7d3fa48a-c73c-4772-ab5f-85f4656acc31_size290x376_cropCenter.jpg"
    ],
    "primaryImg": "https://a88cb3.cdn.akinoncloud.com/products/2022/04/16/173279/7d3fa48a-c73c-4772-ab5f-85f4656acc31_size290x376_cropCenter.jpg",
    "link": "https://www.edwards.com.tr/otrera-navy-card-case-ss22otrera017/",
    "price": [
      {
        "value": "2600 TL",
        "selector": ".product-price .product-sale-price",
        "attribute": "textContent",
        "isJavaScript": false,
        "isShadowDOM": false,
        "numericValue": 2600,
        "unsetPrice": false
      }
    ],
    "videos": [],
    "productNotInStock": false,
    "matchedInfo": {
      "linkSource": "titleElement (matched: .product-item-info  p.product-name a)",
      "matchedSelector": ".list-content-product-item:has(.product-name a)",
      "titleSelectorMatched": ".product-item-info  p.product-name a",
      "imgSelectorMatched": ".product-item-image",
      "videoSelectorMatched": null,
      "bestPriceSelector": ".product-price .product-sale-price",
      "priceExtractedFromShadowDOM": false
    },
    "pageTitle": "Sezonun trend Kadın Çanta ürünleri Edwards Online’da",
    "pageURL": "https://www.edwards.com.tr/canta/",
    "timestamp": "2025-09-20T10:35:35.166Z",
    "imgValid": true,
    "linkValid": true,
    "titleValid": true,
    "pageTitleValid": true,
    "priceValid": true,
    "videoValid": false,
    "mediaType": "image",
    "processId": "mfs4uenlckzuc",
    "index": 3,
    "categories": {
      "productType": [
        "none"
      ]
    },
    "seo": {
      "keywords": [],
      "tags": []
    }
  },
  {
    "title": "OTRERA\nMini Leda Pink",
    "img": [
      "https://a88cb3.cdn.akinoncloud.com/products/2023/04/18/175971/829dbcf2-a16f-411f-b81d-5656b1abbc16_size290x376_cropCenter.jpg"
    ],
    "primaryImg": "https://a88cb3.cdn.akinoncloud.com/products/2023/04/18/175971/829dbcf2-a16f-411f-b81d-5656b1abbc16_size290x376_cropCenter.jpg",
    "link": "https://www.edwards.com.tr/otrera-mini-leda-pink-ss22otrera081/",
    "price": [
      {
        "value": "10300 TL",
        "selector": ".product-price .product-sale-price",
        "attribute": "textContent",
        "isJavaScript": false,
        "isShadowDOM": false,
        "numericValue": 10300,
        "unsetPrice": false
      }
    ],
    "videos": [],
    "productNotInStock": false,
    "matchedInfo": {
      "linkSource": "titleElement (matched: .product-item-info  p.product-name a)",
      "matchedSelector": ".list-content-product-item:has(.product-name a)",
      "titleSelectorMatched": ".product-item-info  p.product-name a",
      "imgSelectorMatched": ".product-item-image",
      "videoSelectorMatched": null,
      "bestPriceSelector": ".product-price .product-sale-price",
      "priceExtractedFromShadowDOM": false
    },
    "pageTitle": "Sezonun trend Kadın Çanta ürünleri Edwards Online’da",
    "pageURL": "https://www.edwards.com.tr/canta/",
    "timestamp": "2025-09-20T10:35:35.168Z",
    "imgValid": true,
    "linkValid": true,
    "titleValid": true,
    "pageTitleValid": true,
    "priceValid": true,
    "videoValid": false,
    "mediaType": "image",
    "processId": "mfs4uenlckzuc",
    "index": 4,
    "categories": {
      "productType": [
        "none"
      ]
    },
    "seo": {
      "keywords": [],
      "tags": []
    }
  }
]