[
  {
    "title": "Beyaz Bucket Çanta",
    "img": [
      "https://sky-static.mavi.com/mnresize/820/1162/1913093-620_image_1.jpg",
      "https://www.mavi.com/kadin/canta/c/1/_ui/responsive/theme-mavi/images/placeholder.jpg"
    ],
    "primaryImg": "//sky-static.mavi.com/mnresize/820/1162/1913093-620_image_1.jpg",
    "link": "https://www.mavi.com/beyaz-bucket-canta/p/1913093-620",
    "price": [],
    "videos": [],
    "productNotInStock": false,
    "matchedInfo": {
      "linkSource": "titleElement (matched: a[title]:not([href='javascript:void(0);'] :not([href='#']):not([href='']))",
      "matchedSelector": ".product-item",
      "matchedProductItemSelectorManual": ".product-item",
      "titleSelectorMatched": "a[title]:not([href='javascript:void(0);'] :not([href='#']):not([href=''])",
      "imgSelectorMatched": ".swiper-slide img",
      "videoSelectorMatched": null,
      "priceSelectorsMatched": [],
      "usedFallbackDocument": true,
      "matchedPageSelector": null
    },
    "pageTitle": "Kadın Çanta Modelleri",
    "pageURL": "https://www.mavi.com/kadin/canta/c/1",
    "timestamp": "2025-08-15T10:21:04.866Z",
    "imgValid": true,
    "linkValid": true,
    "titleValid": true,
    "pageTitleValid": true,
    "priceValid": false
  },
  {
    "title": "Beyaz Bucket Çanta",
    "img": [
      "https://sky-static.mavi.com/mnresize/820/1162/1913093-620_image_1.jpg",
      "https://www.mavi.com/kadin/canta/c/1/_ui/responsive/theme-mavi/images/placeholder.jpg"
    ],
    "primaryImg": "//sky-static.mavi.com/mnresize/820/1162/1913093-620_image_1.jpg",
    "link": "https://www.mavi.com/beyaz-bucket-canta/p/1913093-620",
    "price": [],
    "videos": [],
    "productNotInStock": false,
    "matchedInfo": {
      "linkSource": "titleElement (matched: a[title]:not([href='javascript:void(0);'] :not([href='#']):not([href='']))",
      "matchedSelector": ".product-card",
      "matchedProductItemSelectorManual": ".product-card",
      "titleSelectorMatched": "a[title]:not([href='javascript:void(0);'] :not([href='#']):not([href=''])",
      "imgSelectorMatched": ".swiper-slide img",
      "videoSelectorMatched": null,
      "priceSelectorsMatched": [],
      "usedFallbackDocument": true,
      "matchedPageSelector": null
    },
    "pageTitle": "Kadın Çanta Modelleri",
    "pageURL": "https://www.mavi.com/kadin/canta/c/1",
    "timestamp": "2025-08-15T10:21:04.867Z",
    "imgValid": true,
    "linkValid": true,
    "titleValid": true,
    "pageTitleValid": true,
    "priceValid": false
  },
  {
    "title": "Renkli Hasır Omuz Çantası",
    "img": [
      "https://sky-static.mavi.com/mnresize/820/1162/1911324-70202_image_1.jpg",
      "https://www.mavi.com/kadin/canta/c/1/_ui/responsive/theme-mavi/images/placeholder.jpg"
    ],
    "primaryImg": "//sky-static.mavi.com/mnresize/820/1162/1911324-70202_image_1.jpg",
    "link": "https://www.mavi.com/renkli-hasir-omuz-cantasi/p/1911324-70202",
    "price": [],
    "videos": [],
    "productNotInStock": false,
    "matchedInfo": {
      "linkSource": "titleElement (matched: a[title]:not([href='javascript:void(0);'] :not([href='#']):not([href='']))",
      "matchedSelector": ".product-item",
      "matchedProductItemSelectorManual": ".product-item",
      "titleSelectorMatched": "a[title]:not([href='javascript:void(0);'] :not([href='#']):not([href=''])",
      "imgSelectorMatched": ".swiper-slide img",
      "videoSelectorMatched": null,
      "priceSelectorsMatched": [],
      "usedFallbackDocument": true,
      "matchedPageSelector": null
    },
    "pageTitle": "Kadın Çanta Modelleri",
    "pageURL": "https://www.mavi.com/kadin/canta/c/1",
    "timestamp": "2025-08-15T10:21:04.868Z",
    "imgValid": true,
    "linkValid": true,
    "titleValid": true,
    "pageTitleValid": true,
    "priceValid": false
  },
  {
    "title": "Renkli Hasır Omuz Çantası",
    "img": [
      "https://sky-static.mavi.com/mnresize/820/1162/1911324-70202_image_1.jpg",
      "https://www.mavi.com/kadin/canta/c/1/_ui/responsive/theme-mavi/images/placeholder.jpg"
    ],
    "primaryImg": "//sky-static.mavi.com/mnresize/820/1162/1911324-70202_image_1.jpg",
    "link": "https://www.mavi.com/renkli-hasir-omuz-cantasi/p/1911324-70202",
    "price": [],
    "videos": [],
    "productNotInStock": false,
    "matchedInfo": {
      "linkSource": "titleElement (matched: a[title]:not([href='javascript:void(0);'] :not([href='#']):not([href='']))",
      "matchedSelector": ".product-card",
      "matchedProductItemSelectorManual": ".product-card",
      "titleSelectorMatched": "a[title]:not([href='javascript:void(0);'] :not([href='#']):not([href=''])",
      "imgSelectorMatched": ".swiper-slide img",
      "videoSelectorMatched": null,
      "priceSelectorsMatched": [],
      "usedFallbackDocument": true,
      "matchedPageSelector": null
    },
    "pageTitle": "Kadın Çanta Modelleri",
    "pageURL": "https://www.mavi.com/kadin/canta/c/1",
    "timestamp": "2025-08-15T10:21:04.869Z",
    "imgValid": true,
    "linkValid": true,
    "titleValid": true,
    "pageTitleValid": true,
    "priceValid": false
  },
  {
    "title": "Denim Omuz Çantası",
    "img": [
      "https://sky-static.mavi.com/mnresize/820/1162/1913105-70872_image_1.jpg"
    ],
    "primaryImg": "//sky-static.mavi.com/mnresize/820/1162/1913105-70872_image_1.jpg",
    "link": "https://www.mavi.com/denim-omuz-cantasi/p/1913105-70872",
    "price": [],
    "videos": [],
    "productNotInStock": false,
    "matchedInfo": {
      "linkSource": "titleElement (matched: a[title]:not([href='javascript:void(0);'] :not([href='#']):not([href='']))",
      "matchedSelector": ".product-item",
      "matchedProductItemSelectorManual": ".product-item",
      "titleSelectorMatched": "a[title]:not([href='javascript:void(0);'] :not([href='#']):not([href=''])",
      "imgSelectorMatched": ".swiper-slide img",
      "videoSelectorMatched": null,
      "priceSelectorsMatched": [],
      "usedFallbackDocument": true,
      "matchedPageSelector": null
    },
    "pageTitle": "Kadın Çanta Modelleri",
    "pageURL": "https://www.mavi.com/kadin/canta/c/1",
    "timestamp": "2025-08-15T10:21:04.870Z",
    "imgValid": true,
    "linkValid": true,
    "titleValid": true,
    "pageTitleValid": true,
    "priceValid": false
  }
]