[
  {
    "title": "Kadın Popette Tote Çanta",
    "img": [
      "https://st-tommy.mncdn.com/mnresize/240/321/Content/media/ProductImg/original/638932039078073216.webp",
      "https://st-tommy.mncdn.com/mnresize/375/500/Content/media/ProductImg/original/638932039078073216.webp",
      "https://st-tommy.mncdn.com/mnresize/460/615/Content/media/ProductImg/original/638932039078073216.webp",
      "https://st-tommy.mncdn.com/mnresize/240/321/Content/media/ProductImg/original/638932039079479473.webp",
      "https://st-tommy.mncdn.com/mnresize/375/500/Content/media/ProductImg/original/638932039079479473.webp",
      "https://st-tommy.mncdn.com/mnresize/460/615/Content/media/ProductImg/original/638932039079479473.webp"
    ],
    "primaryImg": "https://st-tommy.mncdn.com/mnresize/240/321/Content/media/ProductImg/original/638932039078073216.webp",
    "link": "https://tr.tommy.com/kadin-popette-tote-canta_202217",
    "price": [
      {
        "value": "4.999,00 TL",
        "selector": ".p-price .one-price",
        "attribute": "textContent",
        "isJavaScript": false,
        "isShadowDOM": false,
        "numericValue": 4999,
        "unsetPrice": false
      }
    ],
    "videos": [],
    "productNotInStock": false,
    "matchedInfo": {
      "linkSource": "titleElement (matched: .p-name a)",
      "matchedSelector": ".p-item.col-6",
      "titleSelectorMatched": ".p-name a",
      "imgSelectorMatched": "[srcset]",
      "videoSelectorMatched": null,
      "bestPriceSelector": ".p-price .one-price",
      "priceExtractedFromShadowDOM": false
    },
    "pageTitle": "Kadın Çanta Modelleri | Tommy Hilfiger",
    "pageURL": "https://tr.tommy.com/kadin-canta",
    "timestamp": "2025-09-20T10:44:59.991Z",
    "imgValid": true,
    "linkValid": true,
    "titleValid": true,
    "pageTitleValid": true,
    "priceValid": true,
    "videoValid": false,
    "mediaType": "image",
    "processId": "mfs56ijv9qm9l",
    "index": 0,
    "categories": {
      "productType": [
        "çanta",
        "tote çanta"
      ],
      "gender": [
        "kadın"
      ]
    },
    "seo": {
      "keywords": [
        "çanta",
        "çantası",
        "bag",
        "çantasi",
        "tote çanta",
        "tote",
        "kadın",
        "kadin",
        "bayan",
        "woman",
        "female"
      ],
      "tags": [
        "çanta",
        "çantası",
        "bag",
        "çantasi",
        "tote çanta",
        "tote",
        "kadın",
        "kadin",
        "bayan",
        "woman",
        "female"
      ]
    }
  },
  {
    "title": "Kadın Popette Mini Tote Çanta",
    "img": [
      "https://st-tommy.mncdn.com/mnresize/240/321/Content/media/ProductImg/original/638932039024322868.webp",
      "https://st-tommy.mncdn.com/mnresize/375/500/Content/media/ProductImg/original/638932039024322868.webp",
      "https://st-tommy.mncdn.com/mnresize/460/615/Content/media/ProductImg/original/638932039024322868.webp",
      "https://st-tommy.mncdn.com/mnresize/240/321/Content/media/ProductImg/original/638932039026198045.webp",
      "https://st-tommy.mncdn.com/mnresize/375/500/Content/media/ProductImg/original/638932039026198045.webp",
      "https://st-tommy.mncdn.com/mnresize/460/615/Content/media/ProductImg/original/638932039026198045.webp"
    ],
    "primaryImg": "https://st-tommy.mncdn.com/mnresize/240/321/Content/media/ProductImg/original/638932039024322868.webp",
    "link": "https://tr.tommy.com/kadin-popette-mini-tote-canta_202216",
    "price": [
      {
        "value": "4.499,00 TL",
        "selector": ".p-price .one-price",
        "attribute": "textContent",
        "isJavaScript": false,
        "isShadowDOM": false,
        "numericValue": 4499,
        "unsetPrice": false
      }
    ],
    "videos": [],
    "productNotInStock": false,
    "matchedInfo": {
      "linkSource": "titleElement (matched: .p-name a)",
      "matchedSelector": ".p-item.col-6",
      "titleSelectorMatched": ".p-name a",
      "imgSelectorMatched": "[srcset]",
      "videoSelectorMatched": null,
      "bestPriceSelector": ".p-price .one-price",
      "priceExtractedFromShadowDOM": false
    },
    "pageTitle": "Kadın Çanta Modelleri | Tommy Hilfiger",
    "pageURL": "https://tr.tommy.com/kadin-canta",
    "timestamp": "2025-09-20T10:44:59.994Z",
    "imgValid": true,
    "linkValid": true,
    "titleValid": true,
    "pageTitleValid": true,
    "priceValid": true,
    "videoValid": false,
    "mediaType": "image",
    "processId": "mfs56ijv9qm9l",
    "index": 1,
    "categories": {
      "productType": [
        "çanta",
        "tote çanta",
        "mini çanta"
      ],
      "gender": [
        "kadın"
      ]
    },
    "seo": {
      "keywords": [
        "çanta",
        "çantası",
        "bag",
        "çantasi",
        "tote çanta",
        "tote",
        "mini çanta",
        "mini",
        "kadın",
        "kadin",
        "bayan",
        "woman",
        "female"
      ],
      "tags": [
        "çanta",
        "çantası",
        "bag",
        "çantasi",
        "tote çanta",
        "tote",
        "mini çanta",
        "mini",
        "kadın",
        "kadin",
        "bayan",
        "woman",
        "female"
      ]
    }
  },
  {
    "title": "Kadın Popette Dome Sırt Çantası",
    "img": [
      "https://st-tommy.mncdn.com/mnresize/240/321/Content/media/ProductImg/original/638932038795414950.webp",
      "https://st-tommy.mncdn.com/mnresize/375/500/Content/media/ProductImg/original/638932038795414950.webp",
      "https://st-tommy.mncdn.com/mnresize/460/615/Content/media/ProductImg/original/638932038795414950.webp",
      "https://st-tommy.mncdn.com/mnresize/240/321/Content/media/ProductImg/original/638932038797290056.webp",
      "https://st-tommy.mncdn.com/mnresize/375/500/Content/media/ProductImg/original/638932038797290056.webp",
      "https://st-tommy.mncdn.com/mnresize/460/615/Content/media/ProductImg/original/638932038797290056.webp"
    ],
    "primaryImg": "https://st-tommy.mncdn.com/mnresize/240/321/Content/media/ProductImg/original/638932038795414950.webp",
    "link": "https://tr.tommy.com/kadin-popette-dome-sirt-cantasi_202211",
    "price": [
      {
        "value": "5.999,00 TL",
        "selector": ".p-price .one-price",
        "attribute": "textContent",
        "isJavaScript": false,
        "isShadowDOM": false,
        "numericValue": 5999,
        "unsetPrice": false
      }
    ],
    "videos": [],
    "productNotInStock": false,
    "matchedInfo": {
      "linkSource": "titleElement (matched: .p-name a)",
      "matchedSelector": ".p-item.col-6",
      "titleSelectorMatched": ".p-name a",
      "imgSelectorMatched": "[srcset]",
      "videoSelectorMatched": null,
      "bestPriceSelector": ".p-price .one-price",
      "priceExtractedFromShadowDOM": false
    },
    "pageTitle": "Kadın Çanta Modelleri | Tommy Hilfiger",
    "pageURL": "https://tr.tommy.com/kadin-canta",
    "timestamp": "2025-09-20T10:44:59.998Z",
    "imgValid": true,
    "linkValid": true,
    "titleValid": true,
    "pageTitleValid": true,
    "priceValid": true,
    "videoValid": false,
    "mediaType": "image",
    "processId": "mfs56ijv9qm9l",
    "index": 2,
    "categories": {
      "productType": [
        "çanta",
        "sırt çantası"
      ],
      "gender": [
        "kadın"
      ]
    },
    "seo": {
      "keywords": [
        "çanta",
        "çantası",
        "bag",
        "çantasi",
        "sırt çantası",
        "sırt",
        "sirt",
        "kadın",
        "kadin",
        "bayan",
        "woman",
        "female"
      ],
      "tags": [
        "çanta",
        "çantası",
        "bag",
        "çantasi",
        "sırt çantası",
        "sırt",
        "sirt",
        "kadın",
        "kadin",
        "bayan",
        "woman",
        "female"
      ]
    }
  },
  {
    "title": "Kadın TH Icon Washbag",
    "img": [
      "https://st-tommy.mncdn.com/mnresize/240/321/Content/media/ProductImg/original/638932038848852855.webp",
      "https://st-tommy.mncdn.com/mnresize/375/500/Content/media/ProductImg/original/638932038848852855.webp",
      "https://st-tommy.mncdn.com/mnresize/460/615/Content/media/ProductImg/original/638932038848852855.webp",
      "https://st-tommy.mncdn.com/mnresize/240/321/Content/media/ProductImg/original/638932038850884016.webp",
      "https://st-tommy.mncdn.com/mnresize/375/500/Content/media/ProductImg/original/638932038850884016.webp",
      "https://st-tommy.mncdn.com/mnresize/460/615/Content/media/ProductImg/original/638932038850884016.webp"
    ],
    "primaryImg": "https://st-tommy.mncdn.com/mnresize/240/321/Content/media/ProductImg/original/638932038848852855.webp",
    "link": "https://tr.tommy.com/kadin-th-icon-washbag_202212",
    "price": [
      {
        "value": "2.999,00 TL",
        "selector": ".p-price .one-price",
        "attribute": "textContent",
        "isJavaScript": false,
        "isShadowDOM": false,
        "numericValue": 2999,
        "unsetPrice": false
      }
    ],
    "videos": [],
    "productNotInStock": false,
    "matchedInfo": {
      "linkSource": "titleElement (matched: .p-name a)",
      "matchedSelector": ".p-item.col-6",
      "titleSelectorMatched": ".p-name a",
      "imgSelectorMatched": "[srcset]",
      "videoSelectorMatched": null,
      "bestPriceSelector": ".p-price .one-price",
      "priceExtractedFromShadowDOM": false
    },
    "pageTitle": "Kadın Çanta Modelleri | Tommy Hilfiger",
    "pageURL": "https://tr.tommy.com/kadin-canta",
    "timestamp": "2025-09-20T10:45:00.001Z",
    "imgValid": true,
    "linkValid": true,
    "titleValid": true,
    "pageTitleValid": true,
    "priceValid": true,
    "videoValid": false,
    "mediaType": "image",
    "processId": "mfs56ijv9qm9l",
    "index": 3,
    "categories": {
      "productType": [
        "none"
      ],
      "gender": [
        "kadın"
      ]
    },
    "seo": {
      "keywords": [
        "kadın",
        "kadin",
        "bayan",
        "woman",
        "female"
      ],
      "tags": [
        "kadın",
        "kadin",
        "bayan",
        "woman",
        "female"
      ]
    }
  },
  {
    "title": "Kadın TH Icon Washbag",
    "img": [
      "https://st-tommy.mncdn.com/mnresize/240/321/Content/media/ProductImg/original/638932038744789485.webp",
      "https://st-tommy.mncdn.com/mnresize/375/500/Content/media/ProductImg/original/638932038744789485.webp",
      "https://st-tommy.mncdn.com/mnresize/460/615/Content/media/ProductImg/original/638932038744789485.webp",
      "https://st-tommy.mncdn.com/mnresize/240/321/Content/media/ProductImg/original/638932038746039566.webp",
      "https://st-tommy.mncdn.com/mnresize/375/500/Content/media/ProductImg/original/638932038746039566.webp",
      "https://st-tommy.mncdn.com/mnresize/460/615/Content/media/ProductImg/original/638932038746039566.webp"
    ],
    "primaryImg": "https://st-tommy.mncdn.com/mnresize/240/321/Content/media/ProductImg/original/638932038744789485.webp",
    "link": "https://tr.tommy.com/kadin-th-icon-washbag_202210",
    "price": [
      {
        "value": "2.749,00 TL",
        "selector": ".p-price .one-price",
        "attribute": "textContent",
        "isJavaScript": false,
        "isShadowDOM": false,
        "numericValue": 2749,
        "unsetPrice": false
      }
    ],
    "videos": [],
    "productNotInStock": false,
    "matchedInfo": {
      "linkSource": "titleElement (matched: .p-name a)",
      "matchedSelector": ".p-item.col-6",
      "titleSelectorMatched": ".p-name a",
      "imgSelectorMatched": "[srcset]",
      "videoSelectorMatched": null,
      "bestPriceSelector": ".p-price .one-price",
      "priceExtractedFromShadowDOM": false
    },
    "pageTitle": "Kadın Çanta Modelleri | Tommy Hilfiger",
    "pageURL": "https://tr.tommy.com/kadin-canta",
    "timestamp": "2025-09-20T10:45:00.005Z",
    "imgValid": true,
    "linkValid": true,
    "titleValid": true,
    "pageTitleValid": true,
    "priceValid": true,
    "videoValid": false,
    "mediaType": "image",
    "processId": "mfs56ijv9qm9l",
    "index": 4,
    "categories": {
      "productType": [
        "none"
      ],
      "gender": [
        "kadın"
      ]
    },
    "seo": {
      "keywords": [
        "kadın",
        "kadin",
        "bayan",
        "woman",
        "female"
      ],
      "tags": [
        "kadın",
        "kadin",
        "bayan",
        "woman",
        "female"
      ]
    }
  }
]