[
  {
    "title": "Çok Bölmeli Kadın Günlük Çanta",
    "img": [
      "https://cdn.tozlu.com/img/640/85/cok-bolmeli-kadin-gunluk-canta-1cf15-159fdb1_1012.webp"
    ],
    "primaryImg": "https://cdn.tozlu.com/img/640/85/cok-bolmeli-kadin-gunluk-canta-1cf15-159fdb1_1012.webp",
    "link": "https://www.tozlu.com/cok-bolmeli-kadin-gunluk-canta-1417179",
    "price": [
      {
        "value": "329,99 TL",
        "selector": ".para-tutar",
        "attribute": "textContent",
        "isJavaScript": false,
        "isShadowDOM": false,
        "numericValue": 329.99,
        "unsetPrice": false
      },
      {
        "value": "296,99 TL",
        "selector": ".para-tutar",
        "attribute": "textContent",
        "isJavaScript": false,
        "isShadowDOM": false,
        "numericValue": 296.99,
        "unsetPrice": false
      }
    ],
    "videos": [],
    "productNotInStock": false,
    "matchedInfo": {
      "linkSource": "linkElement (matched: .product-info a)",
      "matchedSelector": ".product-item",
      "titleSelectorMatched": "h2.product-name",
      "imgSelectorMatched": ".product-item-img",
      "videoSelectorMatched": null,
      "bestPriceSelector": ".para-tutar",
      "priceExtractedFromShadowDOM": false
    },
    "pageTitle": "Kadın Çanta Modelleri ve 2025 Fiyatları | tozlu.com",
    "pageURL": "https://www.tozlu.com/kadin-canta",
    "timestamp": "2025-08-29T10:42:49.556Z",
    "imgValid": true,
    "linkValid": true,
    "titleValid": true,
    "pageTitleValid": true,
    "priceValid": true,
    "videoValid": false,
    "mediaType": "image"
  },
  {
    "title": "Kadın Amblem Detaylı Çift Fermuarlı Cüzdan",
    "img": [
      "https://cdn.tozlu.com/img/640/85/kadin-amblem-detayli-cift-fermuarli-cuzdan-1b557-e7d11.webp"
    ],
    "primaryImg": "https://cdn.tozlu.com/img/640/85/kadin-amblem-detayli-cift-fermuarli-cuzdan-1b557-e7d11.webp",
    "link": "https://www.tozlu.com/kadin-amblem-detayli-cift-fermuarli-cuzdan-1273246",
    "price": [
      {
        "value": "139,99 TL",
        "selector": ".para-tutar",
        "attribute": "textContent",
        "isJavaScript": false,
        "isShadowDOM": false,
        "numericValue": 139.99,
        "unsetPrice": false
      },
      {
        "value": "125,99 TL",
        "selector": ".para-tutar",
        "attribute": "textContent",
        "isJavaScript": false,
        "isShadowDOM": false,
        "numericValue": 125.99,
        "unsetPrice": false
      }
    ],
    "videos": [],
    "productNotInStock": false,
    "matchedInfo": {
      "linkSource": "linkElement (matched: .product-info a)",
      "matchedSelector": ".product-item",
      "titleSelectorMatched": "h2.product-name",
      "imgSelectorMatched": ".product-item-img",
      "videoSelectorMatched": null,
      "bestPriceSelector": ".para-tutar",
      "priceExtractedFromShadowDOM": false
    },
    "pageTitle": "Kadın Çanta Modelleri ve 2025 Fiyatları | tozlu.com",
    "pageURL": "https://www.tozlu.com/kadin-canta",
    "timestamp": "2025-08-29T10:42:49.560Z",
    "imgValid": true,
    "linkValid": true,
    "titleValid": true,
    "pageTitleValid": true,
    "priceValid": true,
    "videoValid": false,
    "mediaType": "image"
  },
  {
    "title": "Kadın Amblem Detaylı Çift Fermuarlı Cüzdan",
    "img": [
      "https://cdn.tozlu.com/img/640/85/kadin-amblem-detayli-cift-fermuarli-cuzdan-1b557-18fb11.webp"
    ],
    "primaryImg": "https://cdn.tozlu.com/img/640/85/kadin-amblem-detayli-cift-fermuarli-cuzdan-1b557-18fb11.webp",
    "link": "https://www.tozlu.com/kadin-amblem-detayli-cift-fermuarli-cuzdan-1273245",
    "price": [
      {
        "value": "139,99 TL",
        "selector": ".para-tutar",
        "attribute": "textContent",
        "isJavaScript": false,
        "isShadowDOM": false,
        "numericValue": 139.99,
        "unsetPrice": false
      },
      {
        "value": "125,99 TL",
        "selector": ".para-tutar",
        "attribute": "textContent",
        "isJavaScript": false,
        "isShadowDOM": false,
        "numericValue": 125.99,
        "unsetPrice": false
      }
    ],
    "videos": [],
    "productNotInStock": false,
    "matchedInfo": {
      "linkSource": "linkElement (matched: .product-info a)",
      "matchedSelector": ".product-item",
      "titleSelectorMatched": "h2.product-name",
      "imgSelectorMatched": ".product-item-img",
      "videoSelectorMatched": null,
      "bestPriceSelector": ".para-tutar",
      "priceExtractedFromShadowDOM": false
    },
    "pageTitle": "Kadın Çanta Modelleri ve 2025 Fiyatları | tozlu.com",
    "pageURL": "https://www.tozlu.com/kadin-canta",
    "timestamp": "2025-08-29T10:42:49.563Z",
    "imgValid": true,
    "linkValid": true,
    "titleValid": true,
    "pageTitleValid": true,
    "priceValid": true,
    "videoValid": false,
    "mediaType": "image"
  },
  {
    "title": "Kadın Baskılı Cüzdan",
    "img": [
      "https://cdn.tozlu.com/img/640/85/kadin-baskili-cuzdan-1b542-108611.webp"
    ],
    "primaryImg": "https://cdn.tozlu.com/img/640/85/kadin-baskili-cuzdan-1b542-108611.webp",
    "link": "https://www.tozlu.com/kadin-baskili-cuzdan-1273010",
    "price": [
      {
        "value": "99,99 TL",
        "selector": ".para-tutar",
        "attribute": "textContent",
        "isJavaScript": false,
        "isShadowDOM": false,
        "numericValue": 99.99,
        "unsetPrice": false
      },
      {
        "value": "89,99 TL",
        "selector": ".para-tutar",
        "attribute": "textContent",
        "isJavaScript": false,
        "isShadowDOM": false,
        "numericValue": 89.99,
        "unsetPrice": false
      }
    ],
    "videos": [],
    "productNotInStock": false,
    "matchedInfo": {
      "linkSource": "linkElement (matched: .product-info a)",
      "matchedSelector": ".product-item",
      "titleSelectorMatched": "h2.product-name",
      "imgSelectorMatched": ".product-item-img",
      "videoSelectorMatched": null,
      "bestPriceSelector": ".para-tutar",
      "priceExtractedFromShadowDOM": false
    },
    "pageTitle": "Kadın Çanta Modelleri ve 2025 Fiyatları | tozlu.com",
    "pageURL": "https://www.tozlu.com/kadin-canta",
    "timestamp": "2025-08-29T10:42:49.565Z",
    "imgValid": true,
    "linkValid": true,
    "titleValid": true,
    "pageTitleValid": true,
    "priceValid": true,
    "videoValid": false,
    "mediaType": "image"
  },
  {
    "title": "Yazı Baskılı Cüzdanlı Kadın Sırt Çantası",
    "img": [
      "https://cdn.tozlu.com/img/640/85/yazi-baskili-cuzdanli-kadin-sirt-cantasi-1a8d1-e031.webp"
    ],
    "primaryImg": "https://cdn.tozlu.com/img/640/85/yazi-baskili-cuzdanli-kadin-sirt-cantasi-1a8d1-e031.webp",
    "link": "https://www.tozlu.com/yazi-baskili-cuzdanli-kadin-sirt-cantasi-1205928",
    "price": [
      {
        "value": "349,99 TL",
        "selector": ".para-tutar",
        "attribute": "textContent",
        "isJavaScript": false,
        "isShadowDOM": false,
        "numericValue": 349.99,
        "unsetPrice": false
      },
      {
        "value": "249,99 TL",
        "selector": ".para-tutar",
        "attribute": "textContent",
        "isJavaScript": false,
        "isShadowDOM": false,
        "numericValue": 249.99,
        "unsetPrice": false
      }
    ],
    "videos": [],
    "productNotInStock": false,
    "matchedInfo": {
      "linkSource": "linkElement (matched: .product-info a)",
      "matchedSelector": ".product-item",
      "titleSelectorMatched": "h2.product-name",
      "imgSelectorMatched": ".product-item-img",
      "videoSelectorMatched": null,
      "bestPriceSelector": ".para-tutar",
      "priceExtractedFromShadowDOM": false
    },
    "pageTitle": "Kadın Çanta Modelleri ve 2025 Fiyatları | tozlu.com",
    "pageURL": "https://www.tozlu.com/kadin-canta",
    "timestamp": "2025-08-29T10:42:49.568Z",
    "imgValid": true,
    "linkValid": true,
    "titleValid": true,
    "pageTitleValid": true,
    "priceValid": true,
    "videoValid": false,
    "mediaType": "image"
  }
]